bybit_to_tradingview/__init__.py
bybit_to_tradingview/cli.py
bybit_to_tradingview-1.0.0.dist-info/METADATA
bybit_to_tradingview-1.0.0.dist-info/WHEEL
bybit_to_tradingview-1.0.0.dist-info/entry_points.txt
bybit_to_tradingview-1.0.0.dist-info/top_level.txt
bybit_to_tradingview-1.0.0.dist-info/RECORD
