Metadata-Version: 2.4
Name: bybit-to-tradingview
Version: 1.0.0
Summary: Python CLI tool to export top 40 Bybit USDT perpetual symbols to TradingView format
Author-email: VanoBond <wholeelottaredd@gmail.com>
License: MIT
Keywords: bybit,tradingview,crypto,export,api
Classifier: Programming Language :: Python :: 3
Classifier: License :: OSI Approved :: MIT License
Classifier: Operating System :: OS Independent
Requires-Python: >=3.7
Requires-Dist: requests
